{
  "data": {
    "Image": "https://github.com/Msiusko/web3privacy/blob/main/static-assets/Computing%20network.png?raw=true",
    "Projects": [
      {
        "Project": "Phala Network",
        "ProjectLink": "https://www.phala.network/en/",
        "Description": "Privacy-Enhanced Permissionless Computing Protocol.",
        "GitHub": "https://github.com/Phala-Network",
        "ProductReadiness": "testnet, 2020",
        "Ecosystem": "Khala on Kusama",
        "Team": "Public",
        "TeamLink": "https://www.phala.network/en/aboutUs/"
      },
      {
        "Project": "Aleph Zero",
        "ProjectLink": "https://alephzero.org",
        "Description": "Privacy-enhancing public blockchain with instant finality.",
        "GitHub": "https://github.com/aleph-zero-foundation",
        "ProductReadiness": "mainnet",
        "Ecosystem": "Aleph",
        "Team": "Public",
        "TeamLink": "https://alephzero.org/the-team"
      },
      {
        "Project": "Findora",
        "ProjectLink": "https://findora.org",
        "Description": "a decentralized, privacy-preserving smart contract platform.",
        "GitHub": "https://github.com/findoranetwork",
        "ProductReadiness": "mainnet",
        "Ecosystem": "multichain",
        "Team": "Public",
        "TeamLink": "https://findora.org/team/"
      },
      {
        "Project": "ARPA",
        "ProjectLink": "https://www.arpanetwork.io/en-US",
        "Description": "Threshold BLS network can serve as the infrastructure of verifiable random number generator (RNG), secure wallet, cross-chain bridge, decentralized custody etc.",
        "GitHub": "https://github.com/ARPA-Network",
        "ProductReadiness": "mainnet, Q2 2023",
        "Ecosystem": "multichain",
        "Team": "anon"
      },
      {
        "Project": "Phoenix",
        "ProjectLink": "https://phoenix.global",
        "Description": "blockchain infrastructure empowering intelligence web3 applications.",
        "GitHub": "https://github.com/phoenixglobal",
        "ProductReadiness": "testnet",
        "Ecosystem": "multichain",
        "Team": "anon"
      },
      {
        "Project": "Privasea",
        "ProjectLink": "https://www.privasea.tech",
        "Description": "Using secure Multi-Party sharing we protect data ownership and privacy, and facilitate secure sharing between different parties so data still can be processed.",
        "GitHub": "-",
        "ProductReadiness": "-",
        "Ecosystem": "multipurpose",
        "Team": "Public",
        "TeamLink": "https://www.privasea.tech/about"
      },
      {
        "Project": "Alaya",
        "ProjectLink": "https://alaya.network/en",
        "Description": "Alaya is a business sandbox and testing field for the next-generation of financial infrastructure of PlatON.",
        "GitHub": "https://github.com/AlayaNetwork",
        "ProductReadiness": "live, 2022",
        "Ecosystem": "Ethereum",
        "Team": "anon"
      },
      {
        "Project": "Nillion",
        "ProjectLink": "https://www.nillion.com",
        "Description": "The Secure Processing Layer of Web3.",
        "Docs": "https://docsend.com/view/7bkgvzagr6ifhwrc",
        "ProductReadiness": "live",
        "Ecosystem": "multichain",
        "Team": "Public",
        "TeamLink": "https://www.linkedin.com/search/results/people/?currentCompany=%5B%2280922042%22%5D&origin=COMPANY_PAGE_CANNED_SEARCH&sid=*cU"
      },
      {
        "Project": "ZkCloud",
        "ProjectLink": "https://aleo.academy/ecosystem/aleo-toolkit/zkcloud/",
        "Description": "Decentralized, Private Computing.",
        "GitHub": "-",
        "ProductReadiness": "testnet",
        "Ecosystem": "Aleo",
        "Team": "Public",
        "TeamLink": "https://www.linkedin.com/search/results/people/?currentCompany=%5B%2242785598%22%5D&origin=COMPANY_PAGE_CANNED_SEARCH&sid=6tr"
      },
      {
        "Project": "PlatOn Network",
        "ProjectLink": "https://www.platon.network/en",
        "Description": "Combining blockchain and privacy-preserving computation technologies, PlatON is building a decentralized and collaborative AI network and global brain to drive the democratization of AI for safe artificial general intelligence.",
        "GitHub": "https://github.com/PlatONnetwork",
        "ProductReadiness": "live",
        "Ecosystem": "Alaya",
        "Team": "Public",
        "TeamLink": "https://www.linkedin.com/search/results/people/?currentCompany=%5B%2214399632%22%5D&origin=COMPANY_PAGE_CANNED_SEARCH&sid=PCz"
      }
    ]
  }
}
